zhruby/__init__.py
zhruby/__main__.py
zhruby/dict.py
zhruby-2.0.3.dist-info/METADATA
zhruby-2.0.3.dist-info/WHEEL
zhruby-2.0.3.dist-info/top_level.txt
zhruby-2.0.3.dist-info/RECORD
