Metadata-Version: 2.1
Name: zhruby
Version: 2.0.3
Summary: Zaonhe Ruby. Output TeX and PDF with Shanghainese ruby from Chinese passages.
Home-page: https://github.com/edward-martyr/zhruby
Author: Edward Martyr
Author-email: edwardmartyr@outlook.com
License: MIT
Platform: UNKNOWN
Requires-Dist: opencc
